pyvtf/__init__.py
pyvtf/catalog.py
pyvtf/catalog_item.py
pyvtf/command_line.py
pyvtf/disk.py
pyvtf/errors.py
pyvtf/login.py
pyvtf/org.py
pyvtf/plugin.py
pyvtf/plugin_stop.py
pyvtf/user.py
pyvtf/vapp.py
pyvtf/vapp_vm.py
pyvtf/vcd_client_ref.py
pyvtf/vdc.py
pyvtf/proto/__init__.py
pyvtf/proto/catalog_item_pb2.py
pyvtf/proto/catalog_item_pb2_grpc.py
pyvtf/proto/disk_pb2.py
pyvtf/proto/disk_pb2_grpc.py
pyvtf/proto/org_pb2.py
pyvtf/proto/org_pb2_grpc.py
pyvtf/proto/pyvcloudprovider_pb2.py
pyvtf/proto/pyvcloudprovider_pb2_grpc.py
pyvtf/proto/user_pb2.py
pyvtf/proto/user_pb2_grpc.py
pyvtf/proto/vapp_pb2.py
pyvtf/proto/vapp_pb2_grpc.py
pyvtf/proto/vapp_vm_pb2.py
pyvtf/proto/vapp_vm_pb2_grpc.py
pyvtf/proto/vdc_pb2.py
pyvtf/proto/vdc_pb2_grpc.py
pyvtf-0.4.dist-info/DESCRIPTION.rst
pyvtf-0.4.dist-info/METADATA
pyvtf-0.4.dist-info/RECORD
pyvtf-0.4.dist-info/WHEEL
pyvtf-0.4.dist-info/entry_points.txt
pyvtf-0.4.dist-info/metadata.json
pyvtf-0.4.dist-info/top_level.txt
