Metadata-Version: 2.0
Name: pyvtf
Version: 0.4
Summary: A Terrform Service Provider for VMware vCloud Director
Home-page: https://github.com/vmware/terraform-provider-vcloud-director
Author: pyvtf.vmware
Author-email: srinarayana@vmware.com
License: BSD-2 License
Project-URL: Bug Reports, https://github.com/vmware/terraform-provider-vcloud-director/issues
Project-URL: Source, https://github.com/vmware/terraform-provider-vcloud-director
Keywords: terraform vcloud director vcd vmware
Platform: UNKNOWN
Classifier: Environment :: Console
Classifier: Intended Audience :: System Administrators
Classifier: Intended Audience :: Developers
Classifier: Operating System :: POSIX :: Linux
Classifier: Operating System :: MacOS :: MacOS X
Classifier: Operating System :: Microsoft :: Windows
Classifier: Programming Language :: Python
Classifier: Programming Language :: Python :: 3.6
Requires-Python: >=3.6
Requires-Dist: argparse
Requires-Dist: grpcio
Requires-Dist: grpcio-tools
Requires-Dist: grpcio-health-checking
Requires-Dist: vcd-cli
Requires-Dist: pyvcloud
